setup.py
docs/index.txt
docs/license.txt
dtopt/COMPARE.py
dtopt/ELLIPSIS.py
dtopt/NORMALIZE_WHITESPACE.py
dtopt/__init__.py
dtopt/tests.py
dtopt.egg-info/PKG-INFO
dtopt.egg-info/SOURCES.txt
dtopt.egg-info/dependency_links.txt
dtopt.egg-info/top_level.txt
dtopt.egg-info/zip-safe
