Metadata-Version: 1.0
Name: dtopt
Version: 0.1
Summary: Add options to doctest examples while they are running
Home-page: http://pypi.python.org/pypi/dtopt/
Author: Ian Bicking
Author-email: ianb@colorstudy.com
License: MIT
Keywords: doctest
Platform: UNKNOWN
Classifier: Development Status :: 4 - Beta
Classifier: Topic :: Software Development :: Testing
